{
  "breakpoints": {
    "375": {
      "name": "page-events",
      "viewportWidth": 375,
      "width": 375,
      "height": 4028,
      "bones": [
        [
          4.2667,
          24,
          91.4667,
          28,
          8
        ],
        [
          4.2667,
          68,
          27.4875,
          37,
          8
        ],
        [
          50.9625,
          68,
          14.3417,
          37,
          8
        ],
        [
          84.5083,
          68,
          11.225,
          37,
          8
        ],
        [
          4.2667,
          154,
          51.175,
          24,
          8
        ],
        [
          86.3875,
          156,
          9.3458,
          21,
          8
        ],
        [
          4.2667,
          202,
          91.4667,
          18,
          8
        ],
        [
          4.2667,
          240,
          91.4667,
          69,
          8
        ],
        [
          4.2667,
          325,
          91.4667,
          69,
          8,
          true
        ],
        [
          37.0083,
          349,
          18.7792,
          21,
          8
        ],
        [
          58.4542,
          351,
          4.5333,
          17,
          "50%"
        ],
        [
          4.2667,
          418,
          91.4667,
          136,
          8,
          true
        ],
        [
          4.2667,
          418,
          91.4667,
          136,
          8
        ],
        [
          7.4667,
          430,
          22.9375,
          32,
          8,
          true
        ],
        [
          12.2667,
          440,
          13.3375,
          12,
          8
        ],
        [
          4.2667,
          611,
          91.4667,
          19,
          8
        ],
        [
          4.2667,
          646,
          91.4667,
          18,
          8
        ],
        [
          4.2667,
          730,
          91.4667,
          136,
          8,
          true
        ],
        [
          4.2667,
          730,
          91.4667,
          136,
          8
        ],
        [
          7.4667,
          742,
          22.9375,
          32,
          8,
          true
        ],
        [
          12.2667,
          752,
          13.3375,
          12,
          8
        ],
        [
          4.2667,
          923,
          91.4667,
          19,
          8
        ],
        [
          4.2667,
          958,
          91.4667,
          18,
          8
        ],
        [
          4.2667,
          1042,
          91.4667,
          136,
          8,
          true
        ],
        [
          4.2667,
          1042,
          91.4667,
          136,
          8
        ],
        [
          7.4667,
          1054,
          22.9375,
          32,
          8,
          true
        ],
        [
          12.2667,
          1064,
          13.3375,
          12,
          8
        ],
        [
          4.2667,
          1235,
          91.4667,
          19,
          8
        ],
        [
          4.2667,
          1270,
          91.4667,
          18,
          8
        ],
        [
          4.2667,
          1354,
          91.4667,
          136,
          8,
          true
        ],
        [
          4.2667,
          1354,
          91.4667,
          136,
          8
        ],
        [
          7.4667,
          1366,
          22.9375,
          32,
          8,
          true
        ],
        [
          12.2667,
          1376,
          13.3375,
          12,
          8
        ],
        [
          4.2667,
          1547,
          91.4667,
          19,
          8
        ],
        [
          4.2667,
          1582,
          91.4667,
          18,
          8
        ],
        [
          4.2667,
          1703,
          24.5,
          24,
          8
        ],
        [
          86.3875,
          1704,
          9.3458,
          21,
          8
        ],
        [
          4.2667,
          1751,
          91.4667,
          18,
          8
        ],
        [
          4.2667,
          1788,
          91.4667,
          69,
          8
        ],
        [
          4.2667,
          1873,
          91.4667,
          69,
          8,
          true
        ],
        [
          37.0083,
          1897,
          18.7792,
          21,
          8
        ],
        [
          58.4542,
          1899,
          4.5333,
          17,
          "50%"
        ],
        [
          4.2667,
          1966,
          91.4667,
          136,
          8,
          true
        ],
        [
          4.2667,
          1966,
          91.4667,
          136,
          8
        ],
        [
          7.4667,
          1978,
          22.9375,
          32,
          8,
          true
        ],
        [
          12.2667,
          1988,
          13.3375,
          12,
          8
        ],
        [
          4.2667,
          2159,
          91.4667,
          19,
          8
        ],
        [
          4.2667,
          2195,
          91.4667,
          18,
          8
        ],
        [
          4.2667,
          2278,
          91.4667,
          136,
          8,
          true
        ],
        [
          4.2667,
          2278,
          91.4667,
          136,
          8
        ],
        [
          7.4667,
          2290,
          22.9375,
          32,
          8,
          true
        ],
        [
          12.2667,
          2300,
          13.3375,
          12,
          8
        ],
        [
          4.2667,
          2471,
          91.4667,
          19,
          8
        ],
        [
          4.2667,
          2507,
          91.4667,
          18,
          8
        ],
        [
          4.2667,
          2590,
          91.4667,
          136,
          8,
          true
        ],
        [
          4.2667,
          2590,
          91.4667,
          136,
          8
        ],
        [
          7.4667,
          2602,
          27.825,
          32,
          8,
          true
        ],
        [
          12.2667,
          2612,
          18.225,
          12,
          8
        ],
        [
          4.2667,
          2783,
          91.4667,
          19,
          8
        ],
        [
          4.2667,
          2819,
          91.4667,
          18,
          8
        ],
        [
          4.2667,
          2902,
          91.4667,
          136,
          8,
          true
        ],
        [
          4.2667,
          2902,
          91.4667,
          136,
          8
        ],
        [
          7.4667,
          2914,
          27.825,
          32,
          8,
          true
        ],
        [
          12.2667,
          2924,
          18.225,
          12,
          8
        ],
        [
          4.2667,
          3095,
          91.4667,
          19,
          8
        ],
        [
          4.2667,
          3131,
          91.4667,
          18,
          8
        ],
        [
          4.2667,
          3226,
          91.4667,
          1,
          8
        ],
        [
          4.2667,
          3259,
          91.4667,
          26,
          8
        ],
        [
          4.2667,
          3309,
          91.4667,
          34,
          8
        ],
        [
          4.2667,
          3359,
          91.4667,
          69,
          8
        ],
        [
          4.2667,
          3444,
          91.4667,
          34,
          8
        ],
        [
          4.2667,
          3494,
          91.4667,
          69,
          8
        ],
        [
          0,
          3595,
          100,
          434,
          8,
          true
        ],
        [
          4.2667,
          3619,
          91.4667,
          19,
          8
        ],
        [
          4.2667,
          3650,
          91.4667,
          19,
          8
        ],
        [
          4.2667,
          3681,
          91.4667,
          19,
          8
        ],
        [
          4.2667,
          3716,
          91.4667,
          20,
          8
        ],
        [
          28.6417,
          3768,
          42.7125,
          72,
          8
        ],
        [
          17.0958,
          3850,
          65.8083,
          20,
          8
        ],
        [
          4.2667,
          3901,
          91.4667,
          24,
          8
        ],
        [
          4.2667,
          3937,
          91.4667,
          21,
          8
        ],
        [
          4.2667,
          3974,
          8,
          30,
          "50%"
        ],
        [
          18.6667,
          3977,
          8.2667,
          25,
          8
        ]
      ]
    },
    "640": {
      "name": "page-events",
      "viewportWidth": 640,
      "width": 640,
      "height": 3995,
      "bones": [
        [
          2.5,
          24,
          95,
          28,
          8
        ],
        [
          2.5,
          68,
          16.106,
          37,
          8
        ],
        [
          50.564,
          68,
          8.4033,
          37,
          8
        ],
        [
          90.9229,
          68,
          6.5771,
          37,
          8
        ],
        [
          2.5,
          154,
          29.9854,
          24,
          8
        ],
        [
          92.0239,
          156,
          5.4761,
          21,
          8
        ],
        [
          2.5,
          202,
          95,
          18,
          8
        ],
        [
          2.5,
          240,
          95,
          69,
          8
        ],
        [
          2.5,
          325,
          95,
          69,
          8,
          true
        ],
        [
          42.3877,
          349,
          11.0034,
          21,
          8
        ],
        [
          54.9536,
          351,
          2.6563,
          17,
          "50%"
        ],
        [
          2.5,
          418,
          95,
          136,
          8,
          true
        ],
        [
          2.5,
          418,
          95,
          136,
          8
        ],
        [
          4.375,
          430,
          13.4399,
          32,
          8,
          true
        ],
        [
          7.1875,
          440,
          7.8149,
          12,
          8
        ],
        [
          2.5,
          611,
          95,
          19,
          8
        ],
        [
          2.5,
          646,
          95,
          18,
          8
        ],
        [
          2.5,
          730,
          95,
          136,
          8,
          true
        ],
        [
          2.5,
          730,
          95,
          136,
          8
        ],
        [
          4.375,
          742,
          13.4399,
          32,
          8,
          true
        ],
        [
          7.1875,
          752,
          7.8149,
          12,
          8
        ],
        [
          2.5,
          923,
          95,
          19,
          8
        ],
        [
          2.5,
          958,
          95,
          18,
          8
        ],
        [
          2.5,
          1042,
          95,
          136,
          8,
          true
        ],
        [
          2.5,
          1042,
          95,
          136,
          8
        ],
        [
          4.375,
          1054,
          13.4399,
          32,
          8,
          true
        ],
        [
          7.1875,
          1064,
          7.8149,
          12,
          8
        ],
        [
          2.5,
          1235,
          95,
          19,
          8
        ],
        [
          2.5,
          1270,
          95,
          18,
          8
        ],
        [
          2.5,
          1354,
          95,
          136,
          8,
          true
        ],
        [
          2.5,
          1354,
          95,
          136,
          8
        ],
        [
          4.375,
          1366,
          13.4399,
          32,
          8,
          true
        ],
        [
          7.1875,
          1376,
          7.8149,
          12,
          8
        ],
        [
          2.5,
          1547,
          95,
          19,
          8
        ],
        [
          2.5,
          1582,
          95,
          18,
          8
        ],
        [
          2.5,
          1703,
          14.3555,
          24,
          8
        ],
        [
          92.0239,
          1704,
          5.4761,
          21,
          8
        ],
        [
          2.5,
          1751,
          95,
          18,
          8
        ],
        [
          2.5,
          1788,
          95,
          69,
          8
        ],
        [
          2.5,
          1873,
          95,
          69,
          8,
          true
        ],
        [
          42.3877,
          1897,
          11.0034,
          21,
          8
        ],
        [
          54.9536,
          1899,
          2.6563,
          17,
          "50%"
        ],
        [
          2.5,
          1966,
          95,
          136,
          8,
          true
        ],
        [
          2.5,
          1966,
          95,
          136,
          8
        ],
        [
          4.375,
          1978,
          13.4399,
          32,
          8,
          true
        ],
        [
          7.1875,
          1988,
          7.8149,
          12,
          8
        ],
        [
          2.5,
          2159,
          95,
          19,
          8
        ],
        [
          2.5,
          2195,
          95,
          18,
          8
        ],
        [
          2.5,
          2278,
          95,
          136,
          8,
          true
        ],
        [
          2.5,
          2278,
          95,
          136,
          8
        ],
        [
          4.375,
          2290,
          13.4399,
          32,
          8,
          true
        ],
        [
          7.1875,
          2300,
          7.8149,
          12,
          8
        ],
        [
          2.5,
          2471,
          95,
          19,
          8
        ],
        [
          2.5,
          2507,
          95,
          18,
          8
        ],
        [
          2.5,
          2590,
          95,
          136,
          8,
          true
        ],
        [
          2.5,
          2590,
          95,
          136,
          8
        ],
        [
          4.375,
          2602,
          16.3037,
          32,
          8,
          true
        ],
        [
          7.1875,
          2612,
          10.6787,
          12,
          8
        ],
        [
          2.5,
          2783,
          95,
          19,
          8
        ],
        [
          2.5,
          2819,
          95,
          18,
          8
        ],
        [
          2.5,
          2902,
          95,
          136,
          8,
          true
        ],
        [
          2.5,
          2902,
          95,
          136,
          8
        ],
        [
          4.375,
          2914,
          16.3037,
          32,
          8,
          true
        ],
        [
          7.1875,
          2924,
          10.6787,
          12,
          8
        ],
        [
          2.5,
          3095,
          95,
          19,
          8
        ],
        [
          2.5,
          3131,
          95,
          18,
          8
        ],
        [
          2.5,
          3226,
          95,
          1,
          8
        ],
        [
          2.5,
          3259,
          95,
          26,
          8
        ],
        [
          2.5,
          3309,
          95,
          17,
          8
        ],
        [
          2.5,
          3342,
          95,
          69,
          8
        ],
        [
          2.5,
          3427,
          95,
          17,
          8
        ],
        [
          2.5,
          3460,
          95,
          69,
          8
        ],
        [
          0,
          3561,
          100,
          434,
          8,
          true
        ],
        [
          2.5,
          3585,
          95,
          19,
          8
        ],
        [
          2.5,
          3616,
          95,
          19,
          8
        ],
        [
          2.5,
          3647,
          95,
          19,
          8
        ],
        [
          2.5,
          3683,
          95,
          20,
          8
        ],
        [
          37.4854,
          3734,
          25.0269,
          72,
          8
        ],
        [
          30.7202,
          3816,
          38.5596,
          20,
          8
        ],
        [
          2.5,
          3868,
          95,
          24,
          8
        ],
        [
          2.5,
          3904,
          95,
          21,
          8
        ],
        [
          2.5,
          3941,
          4.6875,
          30,
          "50%"
        ],
        [
          10.9375,
          3943,
          4.8438,
          25,
          8
        ]
      ]
    },
    "768": {
      "name": "page-events",
      "viewportWidth": 768,
      "width": 768,
      "height": 1625,
      "bones": [
        [
          3.4993,
          24,
          92.9993,
          28,
          8
        ],
        [
          3.4993,
          68,
          13.4216,
          37,
          8
        ],
        [
          50.4679,
          68,
          7.0028,
          37,
          8
        ],
        [
          91.0177,
          68,
          5.481,
          37,
          8
        ],
        [
          3.4993,
          154,
          20.9574,
          48,
          8
        ],
        [
          27.5818,
          168,
          4.5634,
          21,
          8
        ],
        [
          3.4993,
          226,
          28.6458,
          18,
          8
        ],
        [
          36.0819,
          154,
          28.6458,
          69,
          8
        ],
        [
          67.8528,
          154,
          28.6458,
          69,
          8,
          true
        ],
        [
          75.8321,
          178,
          9.1695,
          21,
          8
        ],
        [
          86.3037,
          180,
          2.2135,
          17,
          "50%"
        ],
        [
          3.4993,
          268,
          26.0417,
          136,
          8,
          true
        ],
        [
          3.4993,
          268,
          26.0417,
          136,
          8
        ],
        [
          5.0618,
          280,
          13.2833,
          32,
          8,
          true
        ],
        [
          8.4473,
          290,
          6.5125,
          12,
          8
        ],
        [
          34.2285,
          299,
          12.6444,
          38,
          8
        ],
        [
          34.2285,
          354,
          12.6444,
          18,
          8
        ],
        [
          51.5605,
          268,
          26.0417,
          136,
          8,
          true
        ],
        [
          51.5605,
          268,
          26.0417,
          136,
          8
        ],
        [
          53.123,
          280,
          13.2833,
          32,
          8,
          true
        ],
        [
          56.5084,
          290,
          6.5125,
          12,
          8
        ],
        [
          82.2896,
          299,
          12.6465,
          38,
          8
        ],
        [
          82.2896,
          354,
          12.6465,
          18,
          8
        ],
        [
          3.4993,
          428,
          26.0417,
          136,
          8,
          true
        ],
        [
          3.4993,
          428,
          26.0417,
          136,
          8
        ],
        [
          5.0618,
          440,
          13.2833,
          32,
          8,
          true
        ],
        [
          8.4473,
          450,
          6.5125,
          12,
          8
        ],
        [
          34.2285,
          459,
          12.6444,
          38,
          8
        ],
        [
          34.2285,
          514,
          12.6444,
          18,
          8
        ],
        [
          51.5605,
          428,
          26.0417,
          136,
          8,
          true
        ],
        [
          51.5605,
          428,
          26.0417,
          136,
          8
        ],
        [
          53.123,
          440,
          13.2833,
          32,
          8,
          true
        ],
        [
          56.5084,
          450,
          6.5125,
          12,
          8
        ],
        [
          82.2896,
          459,
          12.6465,
          38,
          8
        ],
        [
          82.2896,
          514,
          12.6465,
          18,
          8
        ],
        [
          3.4993,
          625,
          11.9629,
          24,
          8
        ],
        [
          27.5818,
          626,
          4.5634,
          21,
          8
        ],
        [
          3.4993,
          673,
          28.6458,
          18,
          8
        ],
        [
          36.0819,
          625,
          28.6458,
          69,
          8
        ],
        [
          67.8528,
          625,
          28.6458,
          69,
          8,
          true
        ],
        [
          75.8321,
          649,
          9.1695,
          21,
          8
        ],
        [
          86.3037,
          651,
          2.2135,
          17,
          "50%"
        ],
        [
          3.4993,
          718,
          26.0417,
          136,
          8,
          true
        ],
        [
          3.4993,
          718,
          26.0417,
          136,
          8
        ],
        [
          5.0618,
          730,
          13.2833,
          32,
          8,
          true
        ],
        [
          8.4473,
          740,
          6.5125,
          12,
          8
        ],
        [
          34.2285,
          749,
          12.6444,
          38,
          8
        ],
        [
          34.2285,
          804,
          12.6444,
          18,
          8
        ],
        [
          51.5605,
          718,
          26.0417,
          136,
          8,
          true
        ],
        [
          51.5605,
          718,
          26.0417,
          136,
          8
        ],
        [
          53.123,
          730,
          13.2833,
          32,
          8,
          true
        ],
        [
          56.5084,
          740,
          6.5125,
          12,
          8
        ],
        [
          82.2896,
          749,
          12.6465,
          38,
          8
        ],
        [
          82.2896,
          804,
          12.6465,
          18,
          8
        ],
        [
          3.4993,
          878,
          26.0417,
          136,
          8,
          true
        ],
        [
          3.4993,
          878,
          26.0417,
          136,
          8
        ],
        [
          5.0618,
          890,
          15.6698,
          32,
          8,
          true
        ],
        [
          8.4473,
          900,
          8.8989,
          12,
          8
        ],
        [
          34.2285,
          909,
          12.6444,
          38,
          8
        ],
        [
          34.2285,
          964,
          12.6444,
          18,
          8
        ],
        [
          51.5605,
          878,
          26.0417,
          136,
          8,
          true
        ],
        [
          51.5605,
          878,
          26.0417,
          136,
          8
        ],
        [
          53.123,
          890,
          15.6698,
          32,
          8,
          true
        ],
        [
          56.5084,
          900,
          8.8989,
          12,
          8
        ],
        [
          82.2896,
          909,
          12.6465,
          38,
          8
        ],
        [
          82.2896,
          964,
          12.6465,
          18,
          8
        ],
        [
          3.4993,
          1050,
          92.9993,
          1,
          8
        ],
        [
          3.4993,
          1083,
          92.9993,
          26,
          8
        ],
        [
          3.4993,
          1152,
          44.1549,
          34,
          8
        ],
        [
          52.3417,
          1152,
          44.1569,
          69,
          8
        ],
        [
          3.4993,
          1257,
          44.1549,
          34,
          8
        ],
        [
          52.3417,
          1257,
          44.1569,
          69,
          8
        ],
        [
          0,
          1358,
          100,
          267,
          8,
          true
        ],
        [
          3.4993,
          1383,
          16.7379,
          19,
          8
        ],
        [
          3.4993,
          1414,
          16.7379,
          19,
          8
        ],
        [
          3.4993,
          1445,
          16.7379,
          19,
          8
        ],
        [
          3.4993,
          1535,
          16.7379,
          20,
          8
        ],
        [
          44.2057,
          1413,
          11.5865,
          40,
          8
        ],
        [
          33.9315,
          1463,
          32.133,
          20,
          8
        ],
        [
          79.7607,
          1383,
          16.7379,
          24,
          8
        ],
        [
          79.7607,
          1419,
          16.7379,
          42,
          8
        ],
        [
          79.7607,
          1524,
          3.9063,
          30,
          "50%"
        ],
        [
          86.792,
          1527,
          4.0365,
          25,
          8
        ]
      ]
    },
    "1024": {
      "name": "page-events",
      "viewportWidth": 1024,
      "width": 1024,
      "height": 1608,
      "bones": [
        [
          3.5004,
          28,
          44.7418,
          33,
          8
        ],
        [
          51.7578,
          24,
          10.0662,
          37,
          8
        ],
        [
          74.4812,
          24,
          5.2521,
          37,
          8
        ],
        [
          92.3889,
          24,
          4.1107,
          37,
          8
        ],
        [
          3.5004,
          110,
          16.9327,
          49,
          8
        ],
        [
          22.7768,
          124,
          3.4225,
          21,
          8
        ],
        [
          3.5004,
          183,
          22.699,
          18,
          8
        ],
        [
          48.7579,
          110,
          22.699,
          69,
          8
        ],
        [
          73.8007,
          110,
          22.699,
          69,
          8,
          true
        ],
        [
          79.8096,
          132,
          8.0429,
          25,
          8
        ],
        [
          88.829,
          136,
          1.6602,
          17,
          "50%"
        ],
        [
          3.5004,
          225,
          21.9986,
          136,
          8,
          true
        ],
        [
          3.5004,
          225,
          21.9986,
          136,
          8
        ],
        [
          4.6722,
          237,
          10.4904,
          33,
          8,
          true
        ],
        [
          7.2113,
          247,
          5.4123,
          13,
          8
        ],
        [
          29.0146,
          266,
          18.6417,
          20,
          8
        ],
        [
          29.0146,
          302,
          18.6417,
          18,
          8
        ],
        [
          51.1719,
          225,
          21.9986,
          136,
          8,
          true
        ],
        [
          51.1719,
          225,
          21.9986,
          136,
          8
        ],
        [
          52.3438,
          237,
          10.4904,
          33,
          8,
          true
        ],
        [
          54.8828,
          247,
          5.4123,
          13,
          8
        ],
        [
          76.6861,
          256,
          18.6417,
          39,
          8
        ],
        [
          76.6861,
          312,
          18.6417,
          18,
          8
        ],
        [
          3.5004,
          385,
          21.9986,
          136,
          8,
          true
        ],
        [
          3.5004,
          385,
          21.9986,
          136,
          8
        ],
        [
          4.6722,
          397,
          10.4904,
          33,
          8,
          true
        ],
        [
          7.2113,
          407,
          5.4123,
          13,
          8
        ],
        [
          29.0146,
          416,
          18.6417,
          39,
          8
        ],
        [
          29.0146,
          472,
          18.6417,
          18,
          8
        ],
        [
          51.1719,
          385,
          21.9986,
          136,
          8,
          true
        ],
        [
          51.1719,
          385,
          21.9986,
          136,
          8
        ],
        [
          52.3438,
          397,
          10.4904,
          33,
          8,
          true
        ],
        [
          54.8828,
          407,
          5.4123,
          13,
          8
        ],
        [
          76.6861,
          416,
          18.6417,
          39,
          8
        ],
        [
          76.6861,
          472,
          18.6417,
          18,
          8
        ],
        [
          3.5004,
          582,
          9.1812,
          25,
          8
        ],
        [
          22.7768,
          584,
          3.4225,
          21,
          8
        ],
        [
          3.5004,
          631,
          22.699,
          18,
          8
        ],
        [
          48.7579,
          582,
          22.699,
          69,
          8
        ],
        [
          73.8007,
          582,
          22.699,
          69,
          8,
          true
        ],
        [
          79.8096,
          604,
          8.0429,
          25,
          8
        ],
        [
          88.829,
          608,
          1.6602,
          17,
          "50%"
        ],
        [
          3.5004,
          675,
          21.9986,
          136,
          8,
          true
        ],
        [
          3.5004,
          675,
          21.9986,
          136,
          8
        ],
        [
          4.6722,
          687,
          10.4904,
          33,
          8,
          true
        ],
        [
          7.2113,
          697,
          5.4123,
          13,
          8
        ],
        [
          29.0146,
          706,
          18.6417,
          39,
          8
        ],
        [
          29.0146,
          762,
          18.6417,
          18,
          8
        ],
        [
          51.1719,
          675,
          21.9986,
          136,
          8,
          true
        ],
        [
          51.1719,
          675,
          21.9986,
          136,
          8
        ],
        [
          52.3438,
          687,
          10.4904,
          33,
          8,
          true
        ],
        [
          54.8828,
          697,
          5.4123,
          13,
          8
        ],
        [
          76.6861,
          706,
          18.6417,
          39,
          8
        ],
        [
          76.6861,
          762,
          18.6417,
          18,
          8
        ],
        [
          3.5004,
          835,
          21.9986,
          136,
          8,
          true
        ],
        [
          3.5004,
          835,
          21.9986,
          136,
          8
        ],
        [
          4.6722,
          847,
          12.4741,
          33,
          8,
          true
        ],
        [
          7.2113,
          857,
          7.3959,
          13,
          8
        ],
        [
          29.0146,
          866,
          18.6417,
          39,
          8
        ],
        [
          29.0146,
          922,
          18.6417,
          18,
          8
        ],
        [
          51.1719,
          835,
          21.9986,
          136,
          8,
          true
        ],
        [
          51.1719,
          835,
          21.9986,
          136,
          8
        ],
        [
          52.3438,
          847,
          12.4741,
          33,
          8,
          true
        ],
        [
          54.8828,
          857,
          7.3959,
          13,
          8
        ],
        [
          76.6861,
          866,
          18.6417,
          39,
          8
        ],
        [
          76.6861,
          922,
          18.6417,
          18,
          8
        ],
        [
          3.5004,
          1007,
          92.9993,
          1,
          8
        ],
        [
          3.5004,
          1051,
          92.9993,
          29,
          8
        ],
        [
          3.5004,
          1124,
          44.7418,
          39,
          8
        ],
        [
          51.7578,
          1124,
          44.7418,
          69,
          8
        ],
        [
          3.5004,
          1229,
          44.7418,
          39,
          8
        ],
        [
          51.7578,
          1229,
          44.7418,
          69,
          8
        ],
        [
          0,
          1341,
          100,
          267,
          8,
          true
        ],
        [
          3.5004,
          1373,
          16.7389,
          20,
          8
        ],
        [
          3.5004,
          1405,
          16.7389,
          20,
          8
        ],
        [
          3.5004,
          1437,
          16.7389,
          20,
          8
        ],
        [
          3.5004,
          1524,
          16.7389,
          20,
          8
        ],
        [
          44.4397,
          1403,
          11.1206,
          51,
          8
        ],
        [
          34.8206,
          1465,
          30.3574,
          25,
          8
        ],
        [
          79.7607,
          1373,
          16.7389,
          25,
          8
        ],
        [
          79.7607,
          1410,
          16.7389,
          25,
          8
        ],
        [
          79.7607,
          1514,
          2.9297,
          30,
          "50%"
        ],
        [
          85.0342,
          1517,
          3.0273,
          25,
          8
        ]
      ]
    },
    "1280": {
      "name": "page-events",
      "viewportWidth": 1280,
      "width": 1280,
      "height": 1565,
      "bones": [
        [
          0.4993,
          24,
          48.0933,
          41,
          8
        ],
        [
          51.405,
          24,
          9.27,
          41,
          8
        ],
        [
          74.4336,
          24,
          4.696,
          41,
          8
        ],
        [
          92.887,
          24,
          3.6121,
          41,
          8
        ],
        [
          3.4998,
          114,
          17.5732,
          61,
          8
        ],
        [
          22.948,
          132,
          3.2507,
          25,
          8
        ],
        [
          3.4998,
          199,
          22.699,
          22,
          8
        ],
        [
          48.2886,
          114,
          22.699,
          69,
          8
        ],
        [
          73.8,
          114,
          22.699,
          69,
          8,
          true
        ],
        [
          80.0732,
          133,
          8.0432,
          31,
          8
        ],
        [
          88.8977,
          140,
          1.3281,
          17,
          "50%"
        ],
        [
          3.4998,
          246,
          21.9995,
          136,
          8,
          true
        ],
        [
          3.4998,
          246,
          21.9995,
          136,
          8
        ],
        [
          4.4373,
          258,
          9.4763,
          37,
          8,
          true
        ],
        [
          6.4685,
          268,
          5.4138,
          17,
          8
        ],
        [
          29.2493,
          283,
          18.4058,
          25,
          8
        ],
        [
          29.2493,
          323,
          18.4058,
          22,
          8
        ],
        [
          51.405,
          246,
          21.9995,
          136,
          8,
          true
        ],
        [
          51.405,
          246,
          21.9995,
          136,
          8
        ],
        [
          52.3425,
          258,
          9.4763,
          37,
          8,
          true
        ],
        [
          54.3738,
          268,
          5.4138,
          17,
          8
        ],
        [
          77.1545,
          270,
          18.407,
          49,
          8
        ],
        [
          77.1545,
          336,
          18.407,
          22,
          8
        ],
        [
          3.4998,
          406,
          21.9995,
          136,
          8,
          true
        ],
        [
          3.4998,
          406,
          21.9995,
          136,
          8
        ],
        [
          4.4373,
          418,
          9.4763,
          37,
          8,
          true
        ],
        [
          6.4685,
          428,
          5.4138,
          17,
          8
        ],
        [
          29.2493,
          430,
          18.4058,
          49,
          8
        ],
        [
          29.2493,
          496,
          18.4058,
          22,
          8
        ],
        [
          51.405,
          406,
          21.9995,
          136,
          8,
          true
        ],
        [
          51.405,
          406,
          21.9995,
          136,
          8
        ],
        [
          52.3425,
          418,
          9.4763,
          37,
          8,
          true
        ],
        [
          54.3738,
          428,
          5.4138,
          17,
          8
        ],
        [
          77.1545,
          430,
          18.407,
          49,
          8
        ],
        [
          77.1545,
          496,
          18.407,
          22,
          8
        ],
        [
          3.4998,
          603,
          9.1821,
          31,
          8
        ],
        [
          22.948,
          606,
          3.2507,
          25,
          8
        ],
        [
          3.4998,
          658,
          22.699,
          22,
          8
        ],
        [
          48.2886,
          603,
          22.699,
          69,
          8
        ],
        [
          73.8,
          603,
          22.699,
          69,
          8,
          true
        ],
        [
          80.0732,
          622,
          8.0432,
          31,
          8
        ],
        [
          88.8977,
          629,
          1.3281,
          17,
          "50%"
        ],
        [
          3.4998,
          704,
          21.9995,
          136,
          8,
          true
        ],
        [
          3.4998,
          704,
          21.9995,
          136,
          8
        ],
        [
          4.4373,
          716,
          9.4763,
          37,
          8,
          true
        ],
        [
          6.4685,
          726,
          5.4138,
          17,
          8
        ],
        [
          29.2493,
          729,
          18.4058,
          49,
          8
        ],
        [
          29.2493,
          794,
          18.4058,
          22,
          8
        ],
        [
          51.405,
          704,
          21.9995,
          136,
          8,
          true
        ],
        [
          51.405,
          704,
          21.9995,
          136,
          8
        ],
        [
          52.3425,
          716,
          9.4763,
          37,
          8,
          true
        ],
        [
          54.3738,
          726,
          5.4138,
          17,
          8
        ],
        [
          77.1545,
          729,
          18.407,
          49,
          8
        ],
        [
          77.1545,
          794,
          18.407,
          22,
          8
        ],
        [
          3.4998,
          864,
          21.9995,
          136,
          8,
          true
        ],
        [
          3.4998,
          864,
          21.9995,
          136,
          8
        ],
        [
          4.4373,
          876,
          11.46,
          37,
          8,
          true
        ],
        [
          6.4685,
          886,
          7.3975,
          17,
          8
        ],
        [
          29.2493,
          889,
          18.4058,
          49,
          8
        ],
        [
          29.2493,
          954,
          18.4058,
          22,
          8
        ],
        [
          51.405,
          864,
          21.9995,
          136,
          8,
          true
        ],
        [
          51.405,
          864,
          21.9995,
          136,
          8
        ],
        [
          52.3425,
          876,
          11.46,
          37,
          8,
          true
        ],
        [
          54.3738,
          886,
          7.3975,
          17,
          8
        ],
        [
          77.1545,
          889,
          18.407,
          49,
          8
        ],
        [
          77.1545,
          954,
          18.407,
          22,
          8
        ],
        [
          3.4998,
          1036,
          92.9993,
          1,
          8
        ],
        [
          29.3274,
          1091,
          67.1716,
          37,
          8
        ],
        [
          3.4998,
          1171,
          21.1401,
          74,
          8
        ],
        [
          27.4524,
          1171,
          21.1401,
          69,
          8
        ],
        [
          51.405,
          1171,
          21.1401,
          74,
          8
        ],
        [
          75.3577,
          1171,
          21.1414,
          69,
          8
        ],
        [
          0,
          1298,
          100,
          267,
          8,
          true
        ],
        [
          3.4998,
          1339,
          20.459,
          25,
          8
        ],
        [
          3.4998,
          1376,
          20.459,
          25,
          8
        ],
        [
          3.4998,
          1412,
          20.459,
          25,
          8
        ],
        [
          3.4998,
          1485,
          20.459,
          25,
          8
        ],
        [
          42.9932,
          1369,
          14.0125,
          81,
          8
        ],
        [
          34.8206,
          1460,
          30.3564,
          31,
          8
        ],
        [
          76.04,
          1339,
          20.459,
          31,
          8
        ],
        [
          76.04,
          1382,
          20.459,
          31,
          8
        ],
        [
          76.04,
          1480,
          2.3438,
          30,
          "50%"
        ],
        [
          80.2588,
          1483,
          2.4219,
          25,
          8
        ]
      ]
    },
    "1536": {
      "name": "page-events",
      "viewportWidth": 1536,
      "width": 1536,
      "height": 1701,
      "bones": [
        [
          5.0781,
          24,
          43.75,
          48,
          8
        ],
        [
          51.1719,
          26,
          9.0108,
          46,
          8
        ],
        [
          74.2442,
          26,
          4.4362,
          46,
          8
        ],
        [
          92.7419,
          26,
          3.3518,
          46,
          8
        ],
        [
          3.9063,
          121,
          16.4754,
          72,
          8
        ],
        [
          21.9442,
          142,
          3.2511,
          30,
          8
        ],
        [
          3.9063,
          217,
          21.2891,
          27,
          8
        ],
        [
          51.1719,
          121,
          21.2891,
          69,
          8
        ],
        [
          74.8047,
          121,
          21.2891,
          69,
          8,
          true
        ],
        [
          80.6407,
          138,
          7.8583,
          36,
          8
        ],
        [
          89.15,
          147,
          1.1068,
          17,
          "50%"
        ],
        [
          3.9063,
          268,
          21.2891,
          152,
          8,
          true
        ],
        [
          3.9063,
          268,
          21.2891,
          152,
          8
        ],
        [
          4.6875,
          280,
          8.7992,
          40,
          8,
          true
        ],
        [
          6.3802,
          290,
          5.4138,
          20,
          8
        ],
        [
          28.3203,
          309,
          19.7266,
          29,
          8
        ],
        [
          28.3203,
          353,
          19.7266,
          26,
          8
        ],
        [
          51.1719,
          268,
          21.2891,
          152,
          8,
          true
        ],
        [
          51.1719,
          268,
          21.2891,
          152,
          8
        ],
        [
          51.9531,
          280,
          8.7992,
          40,
          8,
          true
        ],
        [
          53.6458,
          290,
          5.4138,
          20,
          8
        ],
        [
          75.5859,
          294,
          19.7266,
          58,
          8
        ],
        [
          75.5859,
          368,
          19.7266,
          26,
          8
        ],
        [
          3.9063,
          444,
          21.2891,
          152,
          8,
          true
        ],
        [
          3.9063,
          444,
          21.2891,
          152,
          8
        ],
        [
          4.6875,
          456,
          8.7992,
          40,
          8,
          true
        ],
        [
          6.3802,
          466,
          5.4138,
          20,
          8
        ],
        [
          28.3203,
          470,
          19.7266,
          58,
          8
        ],
        [
          28.3203,
          544,
          19.7266,
          26,
          8
        ],
        [
          51.1719,
          444,
          21.2891,
          152,
          8,
          true
        ],
        [
          51.1719,
          444,
          21.2891,
          152,
          8
        ],
        [
          51.9531,
          456,
          8.7992,
          40,
          8,
          true
        ],
        [
          53.6458,
          466,
          5.4138,
          20,
          8
        ],
        [
          75.5859,
          470,
          19.7266,
          58,
          8
        ],
        [
          75.5859,
          544,
          19.7266,
          26,
          8
        ],
        [
          3.9063,
          657,
          8.9712,
          36,
          8
        ],
        [
          21.9442,
          660,
          3.2511,
          30,
          8
        ],
        [
          3.9063,
          717,
          21.2891,
          27,
          8
        ],
        [
          51.1719,
          657,
          21.2891,
          69,
          8
        ],
        [
          74.8047,
          657,
          21.2891,
          69,
          8,
          true
        ],
        [
          80.6407,
          673,
          7.8583,
          36,
          8
        ],
        [
          89.15,
          683,
          1.1068,
          17,
          "50%"
        ],
        [
          3.9063,
          768,
          21.2891,
          152,
          8,
          true
        ],
        [
          3.9063,
          768,
          21.2891,
          152,
          8
        ],
        [
          4.6875,
          780,
          8.7992,
          40,
          8,
          true
        ],
        [
          6.3802,
          790,
          5.4138,
          20,
          8
        ],
        [
          28.3203,
          794,
          19.7266,
          58,
          8
        ],
        [
          28.3203,
          868,
          19.7266,
          26,
          8
        ],
        [
          51.1719,
          768,
          21.2891,
          152,
          8,
          true
        ],
        [
          51.1719,
          768,
          21.2891,
          152,
          8
        ],
        [
          51.9531,
          780,
          8.7992,
          40,
          8,
          true
        ],
        [
          53.6458,
          790,
          5.4138,
          20,
          8
        ],
        [
          75.5859,
          794,
          19.7266,
          58,
          8
        ],
        [
          75.5859,
          868,
          19.7266,
          26,
          8
        ],
        [
          3.9063,
          944,
          21.2891,
          152,
          8,
          true
        ],
        [
          3.9063,
          944,
          21.2891,
          152,
          8
        ],
        [
          4.6875,
          956,
          10.7839,
          40,
          8,
          true
        ],
        [
          6.3802,
          966,
          7.3985,
          20,
          8
        ],
        [
          28.3203,
          970,
          19.7266,
          58,
          8
        ],
        [
          28.3203,
          1044,
          19.7266,
          26,
          8
        ],
        [
          51.1719,
          944,
          21.2891,
          152,
          8,
          true
        ],
        [
          51.1719,
          944,
          21.2891,
          152,
          8
        ],
        [
          51.9531,
          956,
          10.7839,
          40,
          8,
          true
        ],
        [
          53.6458,
          966,
          7.3985,
          20,
          8
        ],
        [
          75.5859,
          985,
          19.7266,
          29,
          8
        ],
        [
          75.5859,
          1029,
          19.7266,
          26,
          8
        ],
        [
          3.9063,
          1132,
          92.1875,
          1,
          8
        ],
        [
          29.1016,
          1197,
          66.9922,
          43,
          8
        ],
        [
          3.9063,
          1283,
          21.2891,
          86,
          8
        ],
        [
          27.5391,
          1283,
          21.2891,
          69,
          8
        ],
        [
          51.1719,
          1283,
          21.2891,
          86,
          8
        ],
        [
          74.8047,
          1283,
          21.2891,
          69,
          8
        ],
        [
          0,
          1433,
          100,
          268,
          8,
          true
        ],
        [
          3.9063,
          1481,
          20.281,
          29,
          8
        ],
        [
          3.9063,
          1522,
          20.281,
          29,
          8
        ],
        [
          3.9063,
          1563,
          20.281,
          29,
          8
        ],
        [
          3.9063,
          1623,
          20.281,
          30,
          8
        ],
        [
          43.0481,
          1511,
          13.9038,
          96,
          8
        ],
        [
          35.1695,
          1617,
          29.6611,
          36,
          8
        ],
        [
          75.8128,
          1481,
          20.281,
          36,
          8
        ],
        [
          75.8128,
          1529,
          20.281,
          36,
          8
        ],
        [
          75.8128,
          1622,
          1.9531,
          30,
          "50%"
        ],
        [
          79.3284,
          1625,
          2.0182,
          25,
          8
        ]
      ]
    }
  },
  "_hash": "eabca2ee7ff3e0ab926fbc1fe2ed13e1"
}